LICENSE
README.md
setup.cfg
setup.py
src/module_qlr/__init__.py
src/module_qlr/filesystem.py
src/module_qlr/module_qlr.py
src/module_qlr.egg-info/PKG-INFO
src/module_qlr.egg-info/SOURCES.txt
src/module_qlr.egg-info/dependency_links.txt
src/module_qlr.egg-info/requires.txt
src/module_qlr.egg-info/top_level.txt
src/module_qlr/data/Line String.qlr
src/module_qlr/data/Point.qlr
src/module_qlr/data/Polygon.qlr
src/module_qlr/data/PolygonGraduate.qlr
src/module_qlr/data/barrier.qlr
src/module_qlr/data/damage.qlr
src/module_qlr/data/infiltration_rate.qlr
src/module_qlr/data/rain1.qlr
src/module_qlr/data/rainfall.qlr
src/module_qlr/data/raster.qlr
src/module_qlr/data/riverevent.qlr
src/module_qlr/data/sand.qlr
src/module_qlr/data/storagetank.qlr